dbks_optimize/__init__.py
dbks_optimize/optimizer.py
dbks_optimize/utils.py
databricks_optimize-0.2.2.dist-info/LICENSE
databricks_optimize-0.2.2.dist-info/METADATA
databricks_optimize-0.2.2.dist-info/WHEEL
databricks_optimize-0.2.2.dist-info/top_level.txt
databricks_optimize-0.2.2.dist-info/RECORD
